ord_mediascout_client/__init__.py
ord_mediascout_client/client.py
ord_mediascout_client/config.py
ord_mediascout_client/feed_models.py
ord_mediascout_client/models.py
ord_mediascout_client-0.0.70.dist-info/METADATA
ord_mediascout_client-0.0.70.dist-info/WHEEL
ord_mediascout_client-0.0.70.dist-info/licenses/LICENSE.txt
ord_mediascout_client-0.0.70.dist-info/RECORD
