Metadata-Version: 2.4
Name: ord_mediascout_client
Version: 0.0.70
Summary: API Client for Mediascout ORD
Project-URL: Homepage, https://github.com/KokocGroup/OrdMediascoutClientAPI
Project-URL: Bug Tracker, https://github.com/KokocGroup/OrdMediascoutClientAPI/issues
Author-email: Alexey Ruzin <ruzin@me.com>, Ilya Chegodayev <lighter97@gmail.com>, Leonid Klimparsky <l.klimparskiy@dev.kokoc.com>
License-File: LICENSE.txt
Classifier: License :: OSI Approved :: MIT License
Classifier: Operating System :: OS Independent
Classifier: Programming Language :: Python :: 3
Requires-Python: >=3.11
Requires-Dist: pydantic<2.0,>=1.10.7
Requires-Dist: python-dotenv>=1.0.0
Requires-Dist: requests>=2.28.2
